pyqmix_web/__init__.py
pyqmix_web/_version.py
pyqmix_web/backend_app.py
pyqmix_web/run.py
pyqmix_web/frontend/__init__.py
pyqmix_web/frontend/build/asset-manifest.json
pyqmix_web/frontend/build/index.html
pyqmix_web/frontend/build/manifest.json
pyqmix_web/frontend/build/precache-manifest.6959efc49b041b8de9c68cc25cdc1105.js
pyqmix_web/frontend/build/pyqmixweb_desktop_icon.ico
pyqmix_web/frontend/build/pyqmixweb_favicon.ico
pyqmix_web/frontend/build/service-worker.js
pyqmix_web/frontend/build/static/css/1.a928c05b.chunk.css
pyqmix_web/frontend/build/static/css/1.a928c05b.chunk.css.map
pyqmix_web/frontend/build/static/css/main.6904a573.chunk.css
pyqmix_web/frontend/build/static/css/main.6904a573.chunk.css.map
pyqmix_web/frontend/build/static/js/1.2bfd2d05.chunk.js
pyqmix_web/frontend/build/static/js/1.2bfd2d05.chunk.js.map
pyqmix_web/frontend/build/static/js/main.e6990cdc.chunk.js
pyqmix_web/frontend/build/static/js/main.e6990cdc.chunk.js.map
pyqmix_web/frontend/build/static/js/runtime~main.57922bd7.js
pyqmix_web/frontend/build/static/js/runtime~main.57922bd7.js.map
pyqmix_web-2019.1.dist-info/LICENSE
pyqmix_web-2019.1.dist-info/METADATA
pyqmix_web-2019.1.dist-info/WHEEL
pyqmix_web-2019.1.dist-info/entry_points.txt
pyqmix_web-2019.1.dist-info/top_level.txt
pyqmix_web-2019.1.dist-info/RECORD
