Metadata-Version: 2.1
Name: pyqmix-web
Version: 2019.1
Summary: Remote-control interface and web-app for pyqmix.
Home-page: https://github.com/psyfood/pyqmix-web
Author: 
Requires-Dist: pyqmix
Requires-Dist: flask
Requires-Dist: flask-restplus
